{
    "id": "mmv_actions_cawiki",
    "slug": "mmv_actions_cawiki",
    "format": "tsv",
    "type": "timeseries",
    "url": "http://stat1001.wikimedia.org/public-datasets/all/multimedia/media-viewer-actions-cawiki.tsv",
    "name": "Actions: cawiki",
    "shortName": "mmv_actions_cawiki",
    "columns": [
        {
            "id": "datestring",
            "label": "datestring",
            "type": "Date"
        },
        {
            "id": "thumbnail",
            "label": "thumbnail click",
            "type": "Number"
        },
        {
            "id": "enlarge",
            "label": "enlarge click",
            "type": "Number"
        },
        {
            "id": "fullscreen",
            "label": "fullscreen",
            "type": "Number"
        },
        {
            "id": "defullscreen",
            "label": "defullscreen",
            "type": "Number"
        },
        {
            "id": "close",
            "label": "close",
            "type": "Number"
        },
        {
            "id": "view-original-file",
            "label": "view original file",
            "type": "Number"
        },
        {
            "id": "file-description-page",
            "label": "description page (below fold)",
            "type": "Number"
        },
        {
            "id": "file-description-page-abovefold",
            "label": "description page (above fold)",
            "type": "Number"
        },
        {
            "id": "use-this-file-open",
            "label": "use this file open",
            "type": "Number"
        },
        {
            "id": "image-view",
            "label": "image view",
            "type": "Number"
        },
        {
            "id": "metadata-open",
            "label": "metadata open",
            "type": "Number"
        },
        {
            "id": "metadata-close",
            "label": "metadata close",
            "type": "Number"
        },
        {
            "id": "next-image",
            "label": "next image",
            "type": "Number"
        },
        {
            "id": "prev-image",
            "label": "prev image",
            "type": "Number"
        },
        {
            "id": "terms-open",
            "label": "terms open",
            "type": "Number"
        },
        {
            "id": "license-page",
            "label": "license page",
            "type": "Number"
        },
        {
            "id": "author-page",
            "label": "author page",
            "type": "Number"
        },
        {
            "id": "source-page",
            "label": "source page",
            "type": "Number"
        },
        {
            "id": "hash-load",
            "label": "hash load",
            "type": "Number"
        },
        {
            "id": "history-navigation",
            "label": "history nagivation",
            "type": "Number"
        },
        {
            "id": "optout-loggedin",
            "label": "logged-in user opting out",
            "type": "Number"
        },
        {
            "id": "optout-anon",
            "label": "anonymous user opting out",
            "type": "Number"
        },
        {
            "id": "optin-loggedin",
            "label": "logged-in user opting in",
            "type": "Number"
        },
        {
            "id": "optin-anon",
            "label": "anonymous user opting in",
            "type": "Number"
        }
    ]
}